berconpy/__init__.py
berconpy/_typed_event.py
berconpy/client.py
berconpy/dispatch.py
berconpy/errors.py
berconpy/ext/arma/__init__.py
berconpy/ext/arma/ban.py
berconpy/ext/arma/cache.py
berconpy/ext/arma/client.py
berconpy/ext/arma/dispatch.py
berconpy/ext/arma/io.py
berconpy/ext/arma/parser.py
berconpy/ext/arma/player.py
berconpy/io.py
berconpy/protocol/__init__.py
berconpy/protocol/base.py
berconpy/protocol/check.py
berconpy/protocol/client.py
berconpy/protocol/errors.py
berconpy/protocol/events.py
berconpy/protocol/packet.py
berconpy/protocol/server.py
berconpy/py.typed
berconpy/utils.py
berconpy-3.1.1.dist-info/licenses/LICENSE
berconpy-3.1.1.dist-info/WHEEL
berconpy-3.1.1.dist-info/METADATA
berconpy-3.1.1.dist-info/RECORD
