Metadata-Version: 2.4
Name: berconpy
Version: 3.1.1
Summary: An async wrapper for the BattlEye RCON protocol
Author: thegamecracks
License-Expression: MIT
License-File: LICENSE
Classifier: Development Status :: 5 - Production/Stable
Classifier: Framework :: AsyncIO
Classifier: Intended Audience :: Developers
Classifier: Programming Language :: Python
Classifier: Programming Language :: Python :: 3
Classifier: Programming Language :: Python :: 3.10
Classifier: Programming Language :: Python :: 3.11
Classifier: Programming Language :: Python :: 3.12
Classifier: Programming Language :: Python :: 3.13
Classifier: Programming Language :: Python :: 3.14
Classifier: Topic :: System :: Networking
Requires-Python: >=3.10
Project-URL: Documentation, https://berconpy.readthedocs.io/en/stable
Project-URL: Homepage, https://github.com/thegamecracks/berconpy
Project-URL: Issue Tracker, https://github.com/thegamecracks/berconpy/issues
